prolog_env/__init__.py
prolog_env/core.py
prolog_env/inference.py
prolog_env-0.1.4.dist-info/LICENSE
prolog_env-0.1.4.dist-info/METADATA
prolog_env-0.1.4.dist-info/WHEEL
prolog_env-0.1.4.dist-info/top_level.txt
prolog_env-0.1.4.dist-info/RECORD
