Metadata-Version: 2.2
Name: prolog-env
Version: 0.1.4
Summary: A Python package providing an environment for AI agents to test their Prolog code.
Home-page: https://github.com/NewJerseyStyle/prolog-env
Author: Yuan XU
Author-email: dev.source@outlook.com
License: MIT License
License-File: LICENSE
Requires-Dist: gymnasium
Requires-Dist: janus-swi
Provides-Extra: toolbox
Requires-Dist: transformers; extra == "toolbox"
Dynamic: author
Dynamic: author-email
Dynamic: description
Dynamic: description-content-type
Dynamic: home-page
Dynamic: license
Dynamic: provides-extra
Dynamic: requires-dist
Dynamic: summary
